[
    {"id" : "11","nome" : "adesivo","link" : "adesivo.webm"},
    {"id" : "18","nome" : "biscoito","link" : "biscoito.webm"},
    {"id" : "14","nome" : "Deus","link" : "Deus.webm"},
    {"id" : "15","nome" : "DVD","link" : "DVD.webm"},
    {"id" : "32","nome" : "flamengo","link" : "flamengo.webm"},
    {"id" : "39","nome" : "impressora","link" : "impressora.webm"},
    {"id" : "29","nome" : "itaipava (Petrópolis)","link" : "itaipava.webm"},
    {"id" : "7","nome" : "memoria","link" : "memoria.webm"},
    {"id" : "28","nome" : "não ouvir","link" : "naoouvir.webm"},
    {"id" : "34","nome" : "pagar","link" : "pagar.webm"},
    {"id" : "37","nome" : "refletir","link" : "refletir.webm"},
    {"id" : "25","nome" : "surdo","link" : "surdo.webm"},
    {"id" : "1","nome" : "tchau","link" : "tchau.webm"},
    {"id" : "30","nome" : "terça-feira","link" : "tercafeira.webm"},
    {"id" : "27","nome" : "xingar","link" : "xingar.webm"},
    {"id" : "31","nome" : "zâmbia","link" : "zambia.webm"}
]
